pyptax/__init__.py
pyptax/cli.py
pyptax/client.py
pyptax/exceptions.py
pyptax/helpers.py
pyptax/models.py
pyptax/ptax.py
pyptax/resources.py
pyptax/settings.py
pyptax-0.5.0.dist-info/LICENSE
pyptax-0.5.0.dist-info/METADATA
pyptax-0.5.0.dist-info/WHEEL
pyptax-0.5.0.dist-info/entry_points.txt
pyptax-0.5.0.dist-info/top_level.txt
pyptax-0.5.0.dist-info/RECORD
